{
  "tema_1": {
    "limpiar_precios": {
      "inputs": {
        "df": {
          "Fecha": [
            "2024-01-01",
            "2024/01/02",
            "03-01-2024",
            "2024.01.04"
          ],
          "Precio_BVC": [
            "$150.500,00",
            "$152.100,00",
            "ERROR",
            "$149.800,00"
          ],
          "Transacciones": [
            1.2,
            1.35,
            1.1,
            950.0
          ]
        }
      },
      "expected": 452400.0,
      "meta": {
        "type": "scalar"
      },
      "codigo_oculto": "CLEAN_101"
    },
    "respuestas_fijas": [
      184.2756500244141,
      414.7215719640967,
      25.478700274236537,
      0.5476373644434596,
      0.0
    ],
    "hash_exito": "6B7FB886"
  },
  "tema_2": {
    "limpiar_precios": {
      "inputs": {
        "df": {
          "Fecha": [
            "2024-01-01",
            "2024/01/02",
            "03-01-2024",
            "2024.01.04"
          ],
          "Precio_BVC": [
            "$150.500,00",
            "$152.100,00",
            "ERROR",
            "$149.800,00"
          ],
          "Transacciones": [
            1.2,
            1.35,
            1.1,
            950.0
          ]
        }
      },
      "expected": 452400.0,
      "meta": {
        "type": "scalar"
      },
      "codigo_oculto": "CLEAN_102"
    },
    "respuestas_fijas": [
      183.6818084716797,
      414.7215719640967,
      25.478700274236537,
      0.5476373644434596,
      0.0
    ],
    "hash_exito": "635C462C"
  },
  "tema_3": {
    "limpiar_precios": {
      "inputs": {
        "df": {
          "Fecha": [
            "2024-01-01",
            "2024/01/02",
            "03-01-2024",
            "2024.01.04"
          ],
          "Precio_BVC": [
            "$150.500,00",
            "$152.100,00",
            "ERROR",
            "$149.800,00"
          ],
          "Transacciones": [
            1.2,
            1.35,
            1.1,
            950.0
          ]
        }
      },
      "expected": 452400.0,
      "meta": {
        "type": "scalar"
      },
      "codigo_oculto": "CLEAN_103"
    },
    "respuestas_fijas": [
      184.0084381103516,
      414.7215719640967,
      25.478700274236537,
      0.5476373644434596,
      0.0
    ],
    "hash_exito": "DB775AB0"
  },
  "tema_4": {
    "limpiar_precios": {
      "inputs": {
        "df": {
          "Fecha": [
            "2024-01-01",
            "2024/01/02",
            "03-01-2024",
            "2024.01.04"
          ],
          "Precio_BVC": [
            "$150.500,00",
            "$152.100,00",
            "ERROR",
            "$149.800,00"
          ],
          "Transacciones": [
            1.2,
            1.35,
            1.1,
            950.0
          ]
        }
      },
      "expected": 452400.0,
      "meta": {
        "type": "scalar"
      },
      "codigo_oculto": "CLEAN_104"
    },
    "respuestas_fijas": [
      181.7419891357422,
      414.7215719640967,
      25.478700274236537,
      0.5476373644434596,
      0.0
    ],
    "hash_exito": "D1719908"
  },
  "tema_5": {
    "limpiar_precios": {
      "inputs": {
        "df": {
          "Fecha": [
            "2024-01-01",
            "2024/01/02",
            "03-01-2024",
            "2024.01.04"
          ],
          "Precio_BVC": [
            "$150.500,00",
            "$152.100,00",
            "ERROR",
            "$149.800,00"
          ],
          "Transacciones": [
            1.2,
            1.35,
            1.1,
            950.0
          ]
        }
      },
      "expected": 452400.0,
      "meta": {
        "type": "scalar"
      },
      "codigo_oculto": "CLEAN_105"
    },
    "respuestas_fijas": [
      180.8017425537109,
      414.7215719640967,
      25.478700274236537,
      0.5476373644434596,
      0.0
    ],
    "hash_exito": "C9805F2D"
  },
  "tema_6": {
    "limpiar_precios": {
      "inputs": {
        "df": {
          "Fecha": [
            "2024-01-01",
            "2024/01/02",
            "03-01-2024",
            "2024.01.04"
          ],
          "Precio_BVC": [
            "$150.500,00",
            "$152.100,00",
            "ERROR",
            "$149.800,00"
          ],
          "Transacciones": [
            1.2,
            1.35,
            1.1,
            950.0
          ]
        }
      },
      "expected": 452400.0,
      "meta": {
        "type": "scalar"
      },
      "codigo_oculto": "CLEAN_106"
    },
    "respuestas_fijas": [
      186.6905670166016,
      414.7215719640967,
      25.478700274236537,
      0.5476373644434596,
      0.0
    ],
    "hash_exito": "35B66A95"
  },
  "tema_7": {
    "limpiar_precios": {
      "inputs": {
        "df": {
          "Fecha": [
            "2024-01-01",
            "2024/01/02",
            "03-01-2024",
            "2024.01.04"
          ],
          "Precio_BVC": [
            "$150.500,00",
            "$152.100,00",
            "ERROR",
            "$149.800,00"
          ],
          "Transacciones": [
            1.2,
            1.35,
            1.1,
            950.0
          ]
        }
      },
      "expected": 452400.0,
      "meta": {
        "type": "scalar"
      },
      "codigo_oculto": "CLEAN_107"
    },
    "respuestas_fijas": [
      189.5904388427734,
      414.7215719640967,
      25.478700274236537,
      0.5476373644434596,
      0.0
    ],
    "hash_exito": "99DA45A8"
  },
  "tema_8": {
    "limpiar_precios": {
      "inputs": {
        "df": {
          "Fecha": [
            "2024-01-01",
            "2024/01/02",
            "03-01-2024",
            "2024.01.04"
          ],
          "Precio_BVC": [
            "$150.500,00",
            "$152.100,00",
            "ERROR",
            "$149.800,00"
          ],
          "Transacciones": [
            1.2,
            1.35,
            1.1,
            950.0
          ]
        }
      },
      "expected": 452400.0,
      "meta": {
        "type": "scalar"
      },
      "codigo_oculto": "CLEAN_108"
    },
    "respuestas_fijas": [
      191.8964691162109,
      414.7215719640967,
      25.478700274236537,
      0.5476373644434596,
      0.0
    ],
    "hash_exito": "9D963496"
  },
  "tema_9": {
    "limpiar_precios": {
      "inputs": {
        "df": {
          "Fecha": [
            "2024-01-01",
            "2024/01/02",
            "03-01-2024",
            "2024.01.04"
          ],
          "Precio_BVC": [
            "$150.500,00",
            "$152.100,00",
            "ERROR",
            "$149.800,00"
          ],
          "Transacciones": [
            1.2,
            1.35,
            1.1,
            950.0
          ]
        }
      },
      "expected": 452400.0,
      "meta": {
        "type": "scalar"
      },
      "codigo_oculto": "CLEAN_109"
    },
    "respuestas_fijas": [
      193.1732177734375,
      414.7215719640967,
      25.478700274236537,
      0.5476373644434596,
      0.0
    ],
    "hash_exito": "62139DBD"
  },
  "tema_10": {
    "limpiar_precios": {
      "inputs": {
        "df": {
          "Fecha": [
            "2024-01-01",
            "2024/01/02",
            "03-01-2024",
            "2024.01.04"
          ],
          "Precio_BVC": [
            "$150.500,00",
            "$152.100,00",
            "ERROR",
            "$149.800,00"
          ],
          "Transacciones": [
            1.2,
            1.35,
            1.1,
            950.0
          ]
        }
      },
      "expected": 452400.0,
      "meta": {
        "type": "scalar"
      },
      "codigo_oculto": "CLEAN_110"
    },
    "respuestas_fijas": [
      192.5002136230469,
      414.7215719640967,
      25.478700274236537,
      0.5476373644434596,
      0.0
    ],
    "hash_exito": "C26FF09C"
  },
  "tema_11": {
    "limpiar_precios": {
      "inputs": {
        "df": {
          "Fecha": [
            "2024-01-01",
            "2024/01/02",
            "03-01-2024",
            "2024.01.04"
          ],
          "Precio_BVC": [
            "$150.500,00",
            "$152.100,00",
            "ERROR",
            "$149.800,00"
          ],
          "Transacciones": [
            1.2,
            1.35,
            1.1,
            950.0
          ]
        }
      },
      "expected": 452400.0,
      "meta": {
        "type": "scalar"
      },
      "codigo_oculto": "CLEAN_111"
    },
    "respuestas_fijas": [
      192.1735992431641,
      414.7215719640967,
      25.478700274236537,
      0.5476373644434596,
      0.0
    ],
    "hash_exito": "109C60A2"
  },
  "tema_12": {
    "limpiar_precios": {
      "inputs": {
        "df": {
          "Fecha": [
            "2024-01-01",
            "2024/01/02",
            "03-01-2024",
            "2024.01.04"
          ],
          "Precio_BVC": [
            "$150.500,00",
            "$152.100,00",
            "ERROR",
            "$149.800,00"
          ],
          "Transacciones": [
            1.2,
            1.35,
            1.1,
            950.0
          ]
        }
      },
      "expected": 452400.0,
      "meta": {
        "type": "scalar"
      },
      "codigo_oculto": "CLEAN_112"
    },
    "respuestas_fijas": [
      190.4416046142578,
      414.7215719640967,
      25.478700274236537,
      0.5476373644434596,
      0.0
    ],
    "hash_exito": "D49CB8BF"
  },
  "tema_13": {
    "limpiar_precios": {
      "inputs": {
        "df": {
          "Fecha": [
            "2024-01-01",
            "2024/01/02",
            "03-01-2024",
            "2024.01.04"
          ],
          "Precio_BVC": [
            "$150.500,00",
            "$152.100,00",
            "ERROR",
            "$149.800,00"
          ],
          "Transacciones": [
            1.2,
            1.35,
            1.1,
            950.0
          ]
        }
      },
      "expected": 452400.0,
      "meta": {
        "type": "scalar"
      },
      "codigo_oculto": "CLEAN_113"
    },
    "respuestas_fijas": [
      189.7586669921875,
      414.7215719640967,
      25.478700274236537,
      0.5476373644434596,
      0.0
    ],
    "hash_exito": "7F44619D"
  },
  "tema_14": {
    "limpiar_precios": {
      "inputs": {
        "df": {
          "Fecha": [
            "2024-01-01",
            "2024/01/02",
            "03-01-2024",
            "2024.01.04"
          ],
          "Precio_BVC": [
            "$150.500,00",
            "$152.100,00",
            "ERROR",
            "$149.800,00"
          ],
          "Transacciones": [
            1.2,
            1.35,
            1.1,
            950.0
          ]
        }
      },
      "expected": 452400.0,
      "meta": {
        "type": "scalar"
      },
      "codigo_oculto": "CLEAN_114"
    },
    "respuestas_fijas": [
      186.1066131591797,
      414.7215719640967,
      25.478700274236537,
      0.5476373644434596,
      0.0
    ],
    "hash_exito": "BA15387E"
  },
  "tema_15": {
    "limpiar_precios": {
      "inputs": {
        "df": {
          "Fecha": [
            "2024-01-01",
            "2024/01/02",
            "03-01-2024",
            "2024.01.04"
          ],
          "Precio_BVC": [
            "$150.500,00",
            "$152.100,00",
            "ERROR",
            "$149.800,00"
          ],
          "Transacciones": [
            1.2,
            1.35,
            1.1,
            950.0
          ]
        }
      },
      "expected": 452400.0,
      "meta": {
        "type": "scalar"
      },
      "codigo_oculto": "CLEAN_115"
    },
    "respuestas_fijas": [
      182.5040588378906,
      414.7215719640967,
      25.478700274236537,
      0.5476373644434596,
      0.0
    ],
    "hash_exito": "2610BAD4"
  },
  "tema_16": {
    "limpiar_precios": {
      "inputs": {
        "df": {
          "Fecha": [
            "2024-01-01",
            "2024/01/02",
            "03-01-2024",
            "2024.01.04"
          ],
          "Precio_BVC": [
            "$150.500,00",
            "$152.100,00",
            "ERROR",
            "$149.800,00"
          ],
          "Transacciones": [
            1.2,
            1.35,
            1.1,
            950.0
          ]
        }
      },
      "expected": 452400.0,
      "meta": {
        "type": "scalar"
      },
      "codigo_oculto": "CLEAN_116"
    },
    "respuestas_fijas": [
      184.9387664794922,
      414.7215719640967,
      25.478700274236537,
      0.5476373644434596,
      0.0
    ],
    "hash_exito": "3ADEE30A"
  },
  "tema_17": {
    "limpiar_precios": {
      "inputs": {
        "df": {
          "Fecha": [
            "2024-01-01",
            "2024/01/02",
            "03-01-2024",
            "2024.01.04"
          ],
          "Precio_BVC": [
            "$150.500,00",
            "$152.100,00",
            "ERROR",
            "$149.800,00"
          ],
          "Transacciones": [
            1.2,
            1.35,
            1.1,
            950.0
          ]
        }
      },
      "expected": 452400.0,
      "meta": {
        "type": "scalar"
      },
      "codigo_oculto": "CLEAN_117"
    },
    "respuestas_fijas": [
      183.9391479492188,
      414.7215719640967,
      25.478700274236537,
      0.5476373644434596,
      0.0
    ],
    "hash_exito": "DB3AF681"
  },
  "tema_18": {
    "limpiar_precios": {
      "inputs": {
        "df": {
          "Fecha": [
            "2024-01-01",
            "2024/01/02",
            "03-01-2024",
            "2024.01.04"
          ],
          "Precio_BVC": [
            "$150.500,00",
            "$152.100,00",
            "ERROR",
            "$149.800,00"
          ],
          "Transacciones": [
            1.2,
            1.35,
            1.1,
            950.0
          ]
        }
      },
      "expected": 452400.0,
      "meta": {
        "type": "scalar"
      },
      "codigo_oculto": "CLEAN_118"
    },
    "respuestas_fijas": [
      185.7503204345703,
      414.7215719640967,
      25.478700274236537,
      0.5476373644434596,
      0.0
    ],
    "hash_exito": "87796EF6"
  },
  "tema_19": {
    "limpiar_precios": {
      "inputs": {
        "df": {
          "Fecha": [
            "2024-01-01",
            "2024/01/02",
            "03-01-2024",
            "2024.01.04"
          ],
          "Precio_BVC": [
            "$150.500,00",
            "$152.100,00",
            "ERROR",
            "$149.800,00"
          ],
          "Transacciones": [
            1.2,
            1.35,
            1.1,
            950.0
          ]
        }
      },
      "expected": 452400.0,
      "meta": {
        "type": "scalar"
      },
      "codigo_oculto": "CLEAN_119"
    },
    "respuestas_fijas": [
      187.3536682128906,
      414.7215719640967,
      25.478700274236537,
      0.5476373644434596,
      0.0
    ],
    "hash_exito": "F5CD7388"
  },
  "tema_20": {
    "limpiar_precios": {
      "inputs": {
        "df": {
          "Fecha": [
            "2024-01-01",
            "2024/01/02",
            "03-01-2024",
            "2024.01.04"
          ],
          "Precio_BVC": [
            "$150.500,00",
            "$152.100,00",
            "ERROR",
            "$149.800,00"
          ],
          "Transacciones": [
            1.2,
            1.35,
            1.1,
            950.0
          ]
        }
      },
      "expected": 452400.0,
      "meta": {
        "type": "scalar"
      },
      "codigo_oculto": "CLEAN_120"
    },
    "respuestas_fijas": [
      187.4625396728516,
      414.7215719640967,
      25.478700274236537,
      0.5476373644434596,
      0.0
    ],
    "hash_exito": "8D5660C5"
  },
  "tema_21": {
    "limpiar_precios": {
      "inputs": {
        "df": {
          "Fecha": [
            "2024-01-01",
            "2024/01/02",
            "03-01-2024",
            "2024.01.04"
          ],
          "Precio_BVC": [
            "$150.500,00",
            "$152.100,00",
            "ERROR",
            "$149.800,00"
          ],
          "Transacciones": [
            1.2,
            1.35,
            1.1,
            950.0
          ]
        }
      },
      "expected": 452400.0,
      "meta": {
        "type": "scalar"
      },
      "codigo_oculto": "CLEAN_121"
    },
    "respuestas_fijas": [
      186.3837585449219,
      414.7215719640967,
      25.478700274236537,
      0.5476373644434596,
      0.0
    ],
    "hash_exito": "920D47C1"
  },
  "tema_22": {
    "limpiar_precios": {
      "inputs": {
        "df": {
          "Fecha": [
            "2024-01-01",
            "2024/01/02",
            "03-01-2024",
            "2024.01.04"
          ],
          "Precio_BVC": [
            "$150.500,00",
            "$152.100,00",
            "ERROR",
            "$149.800,00"
          ],
          "Transacciones": [
            1.2,
            1.35,
            1.1,
            950.0
          ]
        }
      },
      "expected": 452400.0,
      "meta": {
        "type": "scalar"
      },
      "codigo_oculto": "CLEAN_122"
    },
    "respuestas_fijas": [
      187.1468048095703,
      414.7215719640967,
      25.478700274236537,
      0.5476373644434596,
      0.0
    ],
    "hash_exito": "A98924AA"
  },
  "tema_23": {
    "limpiar_precios": {
      "inputs": {
        "df": {
          "Fecha": [
            "2024-01-01",
            "2024/01/02",
            "03-01-2024",
            "2024.01.04"
          ],
          "Precio_BVC": [
            "$150.500,00",
            "$152.100,00",
            "ERROR",
            "$149.800,00"
          ],
          "Transacciones": [
            1.2,
            1.35,
            1.1,
            950.0
          ]
        }
      },
      "expected": 452400.0,
      "meta": {
        "type": "scalar"
      },
      "codigo_oculto": "CLEAN_123"
    },
    "respuestas_fijas": [
      185.4621429443359,
      414.7215719640967,
      25.478700274236537,
      0.5476373644434596,
      0.0
    ],
    "hash_exito": "DFD606F0"
  },
  "tema_24": {
    "limpiar_precios": {
      "inputs": {
        "df": {
          "Fecha": [
            "2024-01-01",
            "2024/01/02",
            "03-01-2024",
            "2024.01.04"
          ],
          "Precio_BVC": [
            "$150.500,00",
            "$152.100,00",
            "ERROR",
            "$149.800,00"
          ],
          "Transacciones": [
            1.2,
            1.35,
            1.1,
            950.0
          ]
        }
      },
      "expected": 452400.0,
      "meta": {
        "type": "scalar"
      },
      "codigo_oculto": "CLEAN_124"
    },
    "respuestas_fijas": [
      183.3711700439453,
      414.7215719640967,
      25.478700274236537,
      0.5476373644434596,
      0.0
    ],
    "hash_exito": "547585A1"
  },
  "tema_25": {
    "limpiar_precios": {
      "inputs": {
        "df": {
          "Fecha": [
            "2024-01-01",
            "2024/01/02",
            "03-01-2024",
            "2024.01.04"
          ],
          "Precio_BVC": [
            "$150.500,00",
            "$152.100,00",
            "ERROR",
            "$149.800,00"
          ],
          "Transacciones": [
            1.2,
            1.35,
            1.1,
            950.0
          ]
        }
      },
      "expected": 452400.0,
      "meta": {
        "type": "scalar"
      },
      "codigo_oculto": "CLEAN_125"
    },
    "respuestas_fijas": [
      182.4892120361328,
      414.7215719640967,
      25.478700274236537,
      0.5476373644434596,
      0.0
    ],
    "hash_exito": "F0E5A126"
  },
  "tema_26": {
    "limpiar_precios": {
      "inputs": {
        "df": {
          "Fecha": [
            "2024-01-01",
            "2024/01/02",
            "03-01-2024",
            "2024.01.04"
          ],
          "Precio_BVC": [
            "$150.500,00",
            "$152.100,00",
            "ERROR",
            "$149.800,00"
          ],
          "Transacciones": [
            1.2,
            1.35,
            1.1,
            950.0
          ]
        }
      },
      "expected": 452400.0,
      "meta": {
        "type": "scalar"
      },
      "codigo_oculto": "CLEAN_126"
    },
    "respuestas_fijas": [
      182.2017974853516,
      414.7215719640967,
      25.478700274236537,
      0.5476373644434596,
      0.0
    ],
    "hash_exito": "74763F0B"
  },
  "tema_27": {
    "limpiar_precios": {
      "inputs": {
        "df": {
          "Fecha": [
            "2024-01-01",
            "2024/01/02",
            "03-01-2024",
            "2024.01.04"
          ],
          "Precio_BVC": [
            "$150.500,00",
            "$152.100,00",
            "ERROR",
            "$149.800,00"
          ],
          "Transacciones": [
            1.2,
            1.35,
            1.1,
            950.0
          ]
        }
      },
      "expected": 452400.0,
      "meta": {
        "type": "scalar"
      },
      "codigo_oculto": "CLEAN_127"
    },
    "respuestas_fijas": [
      180.6657867431641,
      414.7215719640967,
      25.478700274236537,
      0.5476373644434596,
      0.0
    ],
    "hash_exito": "671160B7"
  },
  "tema_28": {
    "limpiar_precios": {
      "inputs": {
        "df": {
          "Fecha": [
            "2024-01-01",
            "2024/01/02",
            "03-01-2024",
            "2024.01.04"
          ],
          "Precio_BVC": [
            "$150.500,00",
            "$152.100,00",
            "ERROR",
            "$149.800,00"
          ],
          "Transacciones": [
            1.2,
            1.35,
            1.1,
            950.0
          ]
        }
      },
      "expected": 452400.0,
      "meta": {
        "type": "scalar"
      },
      "codigo_oculto": "CLEAN_128"
    },
    "respuestas_fijas": [
      179.9225463867188,
      414.7215719640967,
      25.478700274236537,
      0.5476373644434596,
      0.0
    ],
    "hash_exito": "A1A84F0C"
  },
  "tema_29": {
    "limpiar_precios": {
      "inputs": {
        "df": {
          "Fecha": [
            "2024-01-01",
            "2024/01/02",
            "03-01-2024",
            "2024.01.04"
          ],
          "Precio_BVC": [
            "$150.500,00",
            "$152.100,00",
            "ERROR",
            "$149.800,00"
          ],
          "Transacciones": [
            1.2,
            1.35,
            1.1,
            950.0
          ]
        }
      },
      "expected": 452400.0,
      "meta": {
        "type": "scalar"
      },
      "codigo_oculto": "CLEAN_129"
    },
    "respuestas_fijas": [
      180.6757049560547,
      414.7215719640967,
      25.478700274236537,
      0.5476373644434596,
      0.0
    ],
    "hash_exito": "C82333E4"
  },
  "tema_30": {
    "limpiar_precios": {
      "inputs": {
        "df": {
          "Fecha": [
            "2024-01-01",
            "2024/01/02",
            "03-01-2024",
            "2024.01.04"
          ],
          "Precio_BVC": [
            "$150.500,00",
            "$152.100,00",
            "ERROR",
            "$149.800,00"
          ],
          "Transacciones": [
            1.2,
            1.35,
            1.1,
            950.0
          ]
        }
      },
      "expected": 452400.0,
      "meta": {
        "type": "scalar"
      },
      "codigo_oculto": "CLEAN_130"
    },
    "respuestas_fijas": [
      182.7071990966797,
      414.7215719640967,
      25.478700274236537,
      0.5476373644434596,
      0.0
    ],
    "hash_exito": "A97563A3"
  }
}